LICENSE.txt
README.md
setup.py
AlgosandDataStructures/Bellmanford.py
AlgosandDataStructures/BinarySearch.py
AlgosandDataStructures/Dijkstra.py
AlgosandDataStructures/Fenwicktree.py
AlgosandDataStructures/Floydwarshall.py
AlgosandDataStructures/Lowerbound.py
AlgosandDataStructures/Primefactorization.py
AlgosandDataStructures/Stack.py
AlgosandDataStructures/Upperbound.py
AlgosandDataStructures/howtoGraph.py
AlgosandDataStructures.egg-info/PKG-INFO
AlgosandDataStructures.egg-info/SOURCES.txt
AlgosandDataStructures.egg-info/dependency_links.txt
AlgosandDataStructures.egg-info/top_level.txt